MANIFEST.in
README.txt
setup.cfg
setup.py
csci/__init__.py
csci.countdown.egg-info/PKG-INFO
csci.countdown.egg-info/SOURCES.txt
csci.countdown.egg-info/dependency_links.txt
csci.countdown.egg-info/entry_points.txt
csci.countdown.egg-info/namespace_packages.txt
csci.countdown.egg-info/not-zip-safe
csci.countdown.egg-info/paster_plugins.txt
csci.countdown.egg-info/requires.txt
csci.countdown.egg-info/top_level.txt
csci/countdown/README.txt
csci/countdown/__init__.py
csci/countdown/config.py
csci/countdown/configure.zcml
csci/countdown/browser/__init__.py
csci/countdown/browser/configure.zcml
csci/countdown/browser/countdownview.pt
csci/countdown/browser/countdownview.py
csci/countdown/browser/dailytweetview.pt
csci/countdown/browser/dailytweetview.py
csci/countdown/browser/lib/__init__.py
csci/countdown/browser/lib/feedparser.py
csci/countdown/browser/lib/twitter.py
csci/countdown/content/__init__.py
csci/countdown/content/configure.zcml
csci/countdown/content/countdown.py
csci/countdown/interfaces/__init__.py
csci/countdown/interfaces/countdown.py
csci/countdown/portlets/__init__.py
csci/countdown/portlets/configure.zcml
csci/countdown/profiles/default/actions.xml
csci/countdown/profiles/default/factorytool.xml
csci/countdown/profiles/default/metadata.xml
csci/countdown/profiles/default/portlets.xml
csci/countdown/profiles/default/rolemap.xml
csci/countdown/profiles/default/types.xml
csci/countdown/profiles/default/types/actions.xml
csci/countdown/profiles/default/types/countdown.xml
csci/countdown/tests/__init__.py
csci/countdown/tests/base.py
csci/countdown/tests/test_doctest.py