Metadata-Version: 1.0
Name: csci.countdown
Version: 1.5dev
Summary: provides a countdown to an event
Home-page: www.cannonscientific.com
Author: Peter Dyson
Author-email: pdyson@cannonscientific.com
License: GPL
Keywords: plone countdown date time
Platform: UNKNOWN
Classifier: Framework :: Plone
Classifier: Intended Audience :: Developers
Classifier: Topic :: Software Development :: Libraries :: Python Modules
Classifier: License :: OSI Approved :: GNU General Public License (GPL)
